pygidl/__init__.py
pygidl/__main__.py
pygidl/download_images.py
pygidl/google_images.py
pygidl/utils.py
pygidl/version.py
pygidl-0.0.2.dist-info/LICENSE
pygidl-0.0.2.dist-info/METADATA
pygidl-0.0.2.dist-info/WHEEL
pygidl-0.0.2.dist-info/entry_points.txt
pygidl-0.0.2.dist-info/top_level.txt
pygidl-0.0.2.dist-info/RECORD
