Metadata-Version: 2.1
Name: pygidl
Version: 0.0.2
Summary: Asynchronously download Google Images search results
Home-page: https://github.com/parameter-concern/pygidl
Author: Cameron Carpenter
Author-email: parameter.concern@gmail.com
License: MIT
Download-URL: https://github.com/parameter-concern/pygidl/releases/
Project-URL: Bug Tracker, https://github.com/parameter-concern/pygidl/issues/
Project-URL: Source Code, https://github.com/parameter-concern/pygidl/
Platform: UNKNOWN
Classifier: Development Status :: 3 - Alpha
Classifier: Programming Language :: Python :: 3
Classifier: Programming Language :: Python :: 3.7
Classifier: License :: OSI Approved :: MIT License
Requires-Python: >=3.7
Requires-Dist: aiohttp[speedups]
Requires-Dist: beautifulsoup4
Requires-Dist: python-slugify[unidecode]
Requires-Dist: tqdm
